alqueda/__init__.py
alqueda/alqueda.py
alqueda-0.7.dist-info/licenses/LICENSE
alqueda-0.7.dist-info/METADATA
alqueda-0.7.dist-info/WHEEL
alqueda-0.7.dist-info/top_level.txt
alqueda-0.7.dist-info/RECORD
